datasette_psutil/__init__.py
datasette_psutil-0.2.dist-info/LICENSE
datasette_psutil-0.2.dist-info/METADATA
datasette_psutil-0.2.dist-info/WHEEL
datasette_psutil-0.2.dist-info/entry_points.txt
datasette_psutil-0.2.dist-info/top_level.txt
datasette_psutil-0.2.dist-info/RECORD
