Metadata-Version: 2.1
Name: datasette-psutil
Version: 0.2
Summary: Datasette plugin adding a /-/psutil debugging endpoint
Home-page: https://github.com/simonw/datasette-psutil
Author: Simon Willison
License: Apache License, Version 2.0
Platform: UNKNOWN
Requires-Dist: datasette (>=0.44)
Requires-Dist: psutil
Provides-Extra: test
Requires-Dist: pytest ; extra == 'test'
Requires-Dist: pytest-asyncio ; extra == 'test'
Requires-Dist: httpx ; extra == 'test'
